bam_masterdata/__init__.py
bam_masterdata/_version.py
bam_masterdata/logger.py
bam_masterdata/checker/__init__.py
bam_masterdata/checker/checker.py
bam_masterdata/checker/masterdata_validator.py
bam_masterdata/checker/source_loader.py
bam_masterdata/checker/validation_rules/all_validation_rules.json
bam_masterdata/checker/validation_rules/excel_validation_rules.json
bam_masterdata/checker/validation_rules/validation_rules.json
bam_masterdata/cli/__init__.py
bam_masterdata/cli/cli.py
bam_masterdata/cli/entities_to_excel.py
bam_masterdata/cli/entities_to_rdf.py
bam_masterdata/cli/fill_masterdata.py
bam_masterdata/cli/run_parser.py
bam_masterdata/datamodel/__init__.py
bam_masterdata/datamodel/collection_types.py
bam_masterdata/datamodel/dataset_types.py
bam_masterdata/datamodel/object_types.py
bam_masterdata/datamodel/vocabulary_types.py
bam_masterdata/excel/__init__.py
bam_masterdata/excel/excel_to_entities.py
bam_masterdata/metadata/__init__.py
bam_masterdata/metadata/_maps.py
bam_masterdata/metadata/definitions.py
bam_masterdata/metadata/entities.py
bam_masterdata/metadata/entities_dict.py
bam_masterdata/openbis/__init__.py
bam_masterdata/openbis/get_entities.py
bam_masterdata/openbis/login.py
bam_masterdata/parsing/__init__.py
bam_masterdata/parsing/parsing.py
bam_masterdata/utils/__init__.py
bam_masterdata/utils/paths.py
bam_masterdata/utils/users.py
bam_masterdata/utils/utils.py
bam_masterdata-0.8.3.dist-info/licenses/AUTHORS
bam_masterdata-0.8.3.dist-info/licenses/LICENSE
bam_masterdata-0.8.3.dist-info/licenses/LICENSE.datamodel
bam_masterdata-0.8.3.dist-info/licenses/NOTICE
tests/__init__.py
tests/conftest.py
tests/test_logger.py
tests/checker/test_source_loader.py
tests/cli/test_entities_to_excel.py
tests/cli/test_entities_to_rdf.py
tests/cli/test_run_parser.py
tests/data/checker/example01_codedoesnoteexists.xlsx
tests/data/checker/example02_codeexists_proptype_datatypechanged.xlsx
tests/data/checker/example03_codeexists_proptype_contvoccodechanged.xlsx
tests/data/checker/example04_codeexists_proptype_objectcodechanged.xlsx
tests/data/checker/example05_codeexists_proptype_warningdefschanged.xlsx
bam_masterdata-0.8.3.dist-info/METADATA
bam_masterdata-0.8.3.dist-info/WHEEL
bam_masterdata-0.8.3.dist-info/entry_points.txt
bam_masterdata-0.8.3.dist-info/top_level.txt
bam_masterdata-0.8.3.dist-info/RECORD
