Metadata-Version: 2.4
Name: bam-masterdata
Version: 0.8.3
Summary: The BAM Data Store utility tools and masterdata models wrapped in a Python package with a front-end web interface.
Author-email: BAM Data Store <datastore@bam.de>
Maintainer-email: "Jose M. Pizarro" <jose.pizarro-blanco@bam.de>
License: MIT License
Project-URL: Homepage, https://github.com/BAMresearch/bam-masterdata
Project-URL: Bug Tracker, https://github.com/BAMresearch/bam-masterdata/issues
Project-URL: Documentation, https://bamresearch.github.io/bam-masterdata/
Classifier: Natural Language :: English
Classifier: Intended Audience :: Science/Research
Classifier: Operating System :: OS Independent
Classifier: Programming Language :: Python
Classifier: Programming Language :: Python :: 3.10
Classifier: Programming Language :: Python :: 3.11
Classifier: Programming Language :: Python :: 3.12
Requires-Python: >=3.10
License-File: LICENSE
License-File: LICENSE.datamodel
License-File: NOTICE
License-File: AUTHORS
Requires-Dist: pybis~=1.37.1rc4
Requires-Dist: openpyxl
Requires-Dist: click
Requires-Dist: pydantic~=2.10.5
Requires-Dist: rdflib
Requires-Dist: h5py~=3.12.1
Requires-Dist: python-decouple
Requires-Dist: structlog==24.4.0
Provides-Extra: dev
Requires-Dist: mypy==1.0.1; extra == "dev"
Requires-Dist: ruff; extra == "dev"
Requires-Dist: pytest; extra == "dev"
Requires-Dist: pytest-timeout; extra == "dev"
Requires-Dist: pytest-cov; extra == "dev"
Provides-Extra: docu
Requires-Dist: mkdocs-material; extra == "docu"
Requires-Dist: mkdocs-click; extra == "docu"
Requires-Dist: mkdocstrings; extra == "docu"
Requires-Dist: mkdocstrings-python; extra == "docu"
Dynamic: license-file
